pytorch_approximate_retrieval/__init__.py
pytorch_approximate_retrieval/memory.py
pytorch_approximate_retrieval/memory_factory.py
pytorch_approximate_retrieval-0.2.dist-info/LICENSE.MD
pytorch_approximate_retrieval-0.2.dist-info/METADATA
pytorch_approximate_retrieval-0.2.dist-info/WHEEL
pytorch_approximate_retrieval-0.2.dist-info/top_level.txt
pytorch_approximate_retrieval-0.2.dist-info/RECORD
