Metadata-Version: 2.1
Name: pytorch-approximate-retrieval
Version: 0.2
Summary: Approximate KNN retrieval for PyTorch
Home-page: http://github.com/itsdaniele/pytorch_approximate_retrieval
Author: Daniele Paliotta
Author-email: daniele.paliotta@unige.ch
License: MIT
License-File: LICENSE.MD
Requires-Dist: numpy
Requires-Dist: torch (>=1.6)
